youtube_dl_server/__init__.py
youtube_dl_server/__main__.py
youtube_dl_server/app.py
youtube_dl_server/server.py
youtube_dl_server/version.py
youtube_dl_server-0.2.dist-info/DESCRIPTION.rst
youtube_dl_server-0.2.dist-info/entry_points.txt
youtube_dl_server-0.2.dist-info/METADATA
youtube_dl_server-0.2.dist-info/metadata.json
youtube_dl_server-0.2.dist-info/RECORD
youtube_dl_server-0.2.dist-info/top_level.txt
youtube_dl_server-0.2.dist-info/WHEEL
